{"images":{"image_id":157135,"farm_id":"AIF001","crops_id":"C11_L01_01","crops":"상추","kind_type":"로메인","file_path":"/cropsImages/L/L01/AIF001/C11","fname":"C11_L01_01_001_210906090621.jpg","fext":"jpg","width":"1057","height":"1187","create_date":"2021-10-07","date_captured":"2021-09-06 09:06:21","growth_stage":"생육기","leaf":"1","plant_body":"1"},"envrionments":[{"farm_id":"AIF001","receive_date":"2021-09-06 09:05:33","id":0,"ti_value":"22.0","hi_value":"52.0","ci_value":"329","ir_value":"85","tl_value":"20.7","ei_value":"0.12","pl_value":"5.1"},{"farm_id":"AIF001","receive_date":"2021-09-06 09:01:34","id":1,"ti_value":"22.0","hi_value":"53.0","ci_value":"334","ir_value":"81","tl_value":"20.9","ei_value":"0.12","pl_value":"5.1"}],"growth_index":{"corps_id":"C11_L01_01","measured_date":null,"stem_length":null,"leaf_cnt":null,"leaf_width":null,"leaf_length":null,"stem_thick":null,"fr_weight":null},"etc_infor":{"corps_id":"C11_L01_01","create_date":"","inform":""},"annotations":[{"segmentation":[107.76,339.63,842.65,339.63,842.65,743.52,107.76,743.52],"area":296814.72,"bbox":[107.76,339.63,734.89,403.89],"isCrowd":0,"id":0,"image_id":157135,"category_id":0},{"segmentation":[108.31,533.06,649.19,533.06,649.19,698.83,108.31,698.83],"area":89667.08,"bbox":[108.31,533.06,540.88,165.78],"isCrowd":0,"id":1,"image_id":157135,"category_id":1},{"segmentation":[564.37,340.46,750.65,340.46,750.65,610.91,564.37,610.91],"area":50381.28,"bbox":[564.37,340.46,186.28,270.46],"isCrowd":0,"id":2,"image_id":157135,"category_id":2}],"licenses":[{"id":1,"name":"CCMediaService","url":""}],"categories":[{"id":0,"name":"주","supercategory":"none"},{"id":1,"name":"잎","supercategory":"none"},{"id":2,"name":"잎","supercategory":"none"}]}