{"images":{"image_id":571673,"farm_id":"AIF001","crops_id":"C12_L02_01","crops":"케일","kind_type":"맛짱케일","file_path":"/cropsImages/L/L02/AIF001/C12","fname":"C12_L02_01_001_210924101510.jpg","fext":"jpg","width":"2039","height":"2130","create_date":"2021-12-02","date_captured":"2021-09-24 10:15:10","growth_stage":"수확기","leaf":"1","plant_body":"1"},"envrionments":[{"farm_id":"AIF001","receive_date":"2021-09-24 09:57:35","id":0,"ti_value":"22.0","hi_value":"63.0","ci_value":"378","ir_value":"17","tl_value":null,"ei_value":null,"pl_value":null},{"farm_id":"AIF001","receive_date":"2021-09-24 09:51:58","id":1,"ti_value":"22.0","hi_value":"63.0","ci_value":"355","ir_value":"0","tl_value":"20.8","ei_value":"0.16","pl_value":"4.5"}],"growth_index":{"corps_id":"C12_L02_01","measured_date":null,"stem_length":null,"leaf_cnt":null,"leaf_width":null,"leaf_length":null,"stem_thick":null,"fr_weight":null},"etc_infor":{"corps_id":"C12_L02_01","create_date":"","inform":""},"annotations":[{"segmentation":[266.82,79.76,1930.49,79.76,1930.49,2037.51,266.82,2037.51],"area":3257049.94,"bbox":[266.82,79.76,1663.67,1957.75],"isCrowd":0,"id":0,"image_id":571673,"category_id":0},{"segmentation":[452.29,1160.98,1364.75,1160.98,1364.75,1851.13,452.29,1851.13],"area":629734.26,"bbox":[452.29,1160.98,912.46,690.15],"isCrowd":0,"id":1,"image_id":571673,"category_id":1},{"segmentation":[797.01,75.19,1589.67,75.19,1589.67,912.07,797.01,912.07],"area":663361.3,"bbox":[797.01,75.19,792.66,836.88],"isCrowd":0,"id":2,"image_id":571673,"category_id":2}],"licenses":[{"id":1,"name":"CCMediaService","url":""}],"categories":[{"id":0,"name":"주","supercategory":"none"},{"id":1,"name":"잎","supercategory":"none"},{"id":2,"name":"잎","supercategory":"none"}]}